decoder_3to8.v
module decoder_3to8(a,b,c,y0,y1,y2,y3,y4,y5,y6,y7);
    input a,b,c;
    output y0,y1,y2,y3,y4,y5,y6,y7;
    wire a_comp,b_comp,c_comp;

    not n1 (a_comp,a);
    not n2 (b_comp,b);
    not n3 (c_comp,c);

    and a0 (y0,a_comp,b_comp,c_comp);
    and a1 (y1,a_comp,b_comp,c);
    and a2 (y2,a_comp,b,c_comp);
    and a3 (y3,a_comp,b,c);
    and a4 (y4,a,b_comp,c_comp);
    and a5 (y5,a,b_comp,c);
    and a6 (y6,a,b,c_comp);
    and a7 (y7,a,b,c);

endmodule

decoder_3to8_tb.v
`include "decoder_3to8.v"

`timescale 1ns / 1ns

module decoder_3to8_tb();
    reg a,b,c;
    wire y0,y1,y2,y3,y4,y5,y6,y7;
    decoder_3to8 G5 (.a(a), .b(b), .c(c), .y0(y0), .y1(y1), .y2(y2), .y3(y3), .y4(y4), .y5(y5), .y6(y6), .y7(y7));
    initial begin
        $dumpfile("decoder_3to8_tb.vcd");
        $dumpvars(0, decoder_3to8_tb);

        a=0;b=0;c=0;#10;
        a=0;b=0;c=1;#10;
        a=0;b=1;c=0;#10;
        a=0;b=1;c=1;#10;
        a=1;b=0;c=0;#10;
        a=1;b=0;c=1;#10;
        a=1;b=1;c=0;#10;
        a=1;b=1;c=1;#10;
    end
endmodule

decoder_3to8_tb.vcd
$date
	Tue Jan 17 00:11:35 2023
$end
$version
	Icarus Verilog
$end
$timescale
	1ns
$end
$scope module decoder_3to8_tb $end
$var wire 1 ! y7 $end
$var wire 1 " y6 $end
$var wire 1 # y5 $end
$var wire 1 $ y4 $end
$var wire 1 % y3 $end
$var wire 1 & y2 $end
$var wire 1 ' y1 $end
$var wire 1 ( y0 $end
$var reg 1 ) a $end
$var reg 1 * b $end
$var reg 1 + c $end
$scope module G5 $end
$var wire 1 ) a $end
$var wire 1 , a_comp $end
$var wire 1 * b $end
$var wire 1 - b_comp $end
$var wire 1 + c $end
$var wire 1 . c_comp $end
$var wire 1 ( y0 $end
$var wire 1 ' y1 $end
$var wire 1 & y2 $end
$var wire 1 % y3 $end
$var wire 1 $ y4 $end
$var wire 1 # y5 $end
$var wire 1 " y6 $end
$var wire 1 ! y7 $end
$upscope $end
$upscope $end
$enddefinitions $end
$comment Show the parameter values. $end
$dumpall
$end
#0
$dumpvars
1.
1-
1,
0+
0*
0)
1(
0'
0&
0%
0$
0#
0"
0!
$end
#10
0(
0.
1'
1+
#20
1&
1.
0'
0-
0+
1*
#30
0&
0.
1%
1+
#40
1$
1.
1-
0%
0,
0+
0*
1)
#50
0$
0.
1#
1+
#60
1"
1.
0#
0-
0+
1*
#70
0"
0.
1!
1+
