decoder_3to8_en.v
module decoder_3to8_en (inp,enab,y);
    input [2:0] inp;
    input enab;
    output [7:0] y;
        reg [7:0] y;

    always @(inp or enab)
        begin
            if(enab) begin
                y=8'b00000000;
                case(inp)
                    3'b000: y[0]=1'b1;
                    3'b001: y[1]=1'b1;
                    3'b010: y[2]=1'b1;
                    3'b011: y[3]=1'b1;
                    3'b100: y[4]=1'b1;
                    3'b101: y[5]=1'b1;
                    3'b110: y[6]=1'b1;
                    3'b111: y[7]=1'b1;
                    default: y=8'b00000000;
                endcase
            end
            else begin
                y=8'b00000000;
            end
        end
endmodule

decoder_3to8_en_tb.v
`include "decoder_3to8_en.v"

module decoder_3to8_en_tb();
    reg [2:0] inp;
    reg enab;
    wire [7:0] y;

    decoder_3to8_en G5 (.inp(inp),.enab(enab),.y(y));

    initial begin
        $dumpfile("decoder_3to8_en_tb.vcd");
        $dumpvars(0, decoder_3to8_en_tb);

        enab=0;inp=5;#10;
        enab=1;inp=0;#10;
        enab=1;inp=1;#10;
        enab=1;inp=2;#10;
        enab=1;inp=3;#10;
        enab=1;inp=4;#10;
        enab=1;inp=5;#10;
        enab=1;inp=6;#10;
        enab=1;inp=7;#10;
        enab=0;inp=0;#10;
    end

endmodule

decoder_3to8_en_tb.vcd
$date
	Wed Jan 18 13:38:02 2023
$end
$version
	Icarus Verilog
$end
$timescale
	1s
$end
$scope module decoder_3to8_en_tb $end
$var wire 8 ! y [7:0] $end
$var reg 1 " enab $end
$var reg 3 # inp [2:0] $end
$scope module G5 $end
$var wire 1 " enab $end
$var wire 3 $ inp [2:0] $end
$var reg 8 % y [7:0] $end
$upscope $end
$upscope $end
$enddefinitions $end
$comment Show the parameter values. $end
$dumpall
$end
#0
$dumpvars
b0 %
b101 $
b101 #
0"
b0 !
$end
#10
b1 !
b1 %
b0 #
b0 $
1"
#20
b10 !
b10 %
b1 #
b1 $
#30
b100 !
b100 %
b10 #
b10 $
#40
b1000 !
b1000 %
b11 #
b11 $
#50
b10000 !
b10000 %
b100 #
b100 $
#60
b100000 !
b100000 %
b101 #
b101 $
#70
b1000000 !
b1000000 %
b110 #
b110 $
#80
b10000000 !
b10000000 %
b111 #
b111 $
#90
b0 !
b0 %
b0 #
b0 $
0"
