full_subtractor.v
module full_subtractor(x,y,bin,bout,d);
    input wire x,y,bin;
    output wire bout,d;
    wire b_temp,d_temp,a1,a2,a3,n1;
    
    xor s1 (d_temp,x,y);
    xor s2 (d,bin,d_temp);

    not c1 (n1,x);
    and c2 (a1,n1,bin);
    and c3 (a2,n1,y);
    and c4 (a3,y,bin);
    or c5 (b_temp,a1,a2);
    or c6 (bout,a3,b_temp);

endmodule

full_subtractor_tb.v
`include "full_subtractor.v"

`timescale 1ns / 1ns

module full_subtractor_tb();
    reg x,y,bin;
    wire bout,d;
    full_subtractor G1 (.x(x),.y(y),.bin(bin),.bout(bout),.d(d));
    initial begin
        $dumpfile("full_subtractor_tb.vcd");
        $dumpvars(0, full_subtractor_tb);

        x=0; y=0; bin=0; #10;
        x=0; y=1; bin=0; #10;
        x=1; y=0; bin=0; #10;
        x=1; y=1; bin=0; #10;
        x=0; y=0; bin=1; #10;
        x=0; y=1; bin=1; #10;
        x=1; y=0; bin=1; #10;
        x=1; y=1; bin=1; #10;
    end
endmodule

full_subtractor_tb.vcd
$date
	Wed Jan 25 15:24:00 2023
$end
$version
	Icarus Verilog
$end
$timescale
	1ns
$end
$scope module full_subtractor_tb $end
$var wire 1 ! d $end
$var wire 1 " bout $end
$var reg 1 # bin $end
$var reg 1 $ x $end
$var reg 1 % y $end
$scope module G1 $end
$var wire 1 & a1 $end
$var wire 1 ' a2 $end
$var wire 1 ( a3 $end
$var wire 1 ) b_temp $end
$var wire 1 # bin $end
$var wire 1 " bout $end
$var wire 1 ! d $end
$var wire 1 * d_temp $end
$var wire 1 + n1 $end
$var wire 1 $ x $end
$var wire 1 % y $end
$upscope $end
$upscope $end
$enddefinitions $end
$comment Show the parameter values. $end
$dumpall
$end
#0
$dumpvars
1+
0*
0)
0(
0'
0&
0%
0$
0#
0"
0!
$end
#10
1"
1!
1)
1*
1'
1%
#20
0"
0)
0'
0+
0%
1$
#30
0!
0*
1%
#40
1"
1)
1!
1&
1+
1#
0%
0$
#50
0!
1*
1'
1(
1%
#60
0"
0)
0&
0'
0(
0+
0%
1$
#70
1!
1"
0*
1(
1%
