mem.v
module single_port_memory(
    input clk,              // clock input
    input rst,              // reset input
    input mode,             // mode input (0 for scribble mode, 1 for interpret mode)
    input we,               // write enable input
    input [4:0] addr,       // address input (5-bit address for 32 words)
    input [31:0] data_in,   // input data
    output reg [31:0] data_out // output data
);

reg [31:0] mem [0:31];    // 32x32 memory array
integer i;
always @(posedge clk, posedge rst) begin
    if (rst) begin        // reset memory and output to 0
        data_out <= 0;
        for (i = 0; i < 32; i = i + 1) begin
            mem[i] <= 0;
        end
    end
    else if (we && mode == 0) begin  // scribble mode
        mem[addr] <= data_in;
        data_out <= data_in;  // drive input data on output
    end
    else if (we==0 && mode==1) begin             // interpret mode
        data_out <= mem[addr];  // provide output based on memory content at given address
    end
    else if (we && mode==1) begin
        mem[addr] <= data_in;             // interpret mode
        data_out <= mem[addr];  // provide output based on memory content at given address
    end
end

endmodule

mem_tb.v
`include "mem.v"

module single_port_memory_tb;

reg clk;
reg rst;
reg mode;
reg we;
reg [4:0] addr;
reg [31:0] data_in;
wire [31:0] data_out;

single_port_memory spm(
    .clk(clk),
    .rst(rst),
    .mode(mode),
    .we(we),
    .addr(addr),
    .data_in(data_in),
    .data_out(data_out)
);

initial begin
    $dumpfile("mem.vcd");
    $dumpvars(0,single_port_memory_tb);
    clk = 0;
    rst = 1;
    mode = 0;
    we = 0;
    addr = 5'b00000;
    data_in = 0;
    #20; rst=0;
    #20;
    addr=5;
    data_in=10;
    we=1;mode=0;#20;
    data_in=11;
    we=1;mode=0;#20;
    // data_in=10;
    // we=0;mode=1;#20;
    // data_in=11;
    // we=0;mode=1;#20;
    // data_in=10;
    // we=1;mode=0;#20;
    // data_in=11;
    // we=1;mode=0;#20;
    data_in=10;
    we=1;mode=1;#20;
    data_in=11;
    we=1;mode=1;#20;
    $finish;
end

always #5 clk = ~clk;

endmodule

mem.vcd
$date
	Wed Feb 15 13:28:13 2023
$end
$version
	Icarus Verilog
$end
$timescale
	1s
$end
$scope module single_port_memory_tb $end
$var wire 32 ! data_out [31:0] $end
$var reg 5 " addr [4:0] $end
$var reg 1 # clk $end
$var reg 32 $ data_in [31:0] $end
$var reg 1 % mode $end
$var reg 1 & rst $end
$var reg 1 ' we $end
$scope module spm $end
$var wire 5 ( addr [4:0] $end
$var wire 1 # clk $end
$var wire 32 ) data_in [31:0] $end
$var wire 1 % mode $end
$var wire 1 & rst $end
$var wire 1 ' we $end
$var reg 32 * data_out [31:0] $end
$var integer 32 + i [31:0] $end
$upscope $end
$upscope $end
$enddefinitions $end
$comment Show the parameter values. $end
$dumpall
$end
#0
$dumpvars
b100000 +
b0 *
b0 )
b0 (
0'
1&
0%
b0 $
0#
b0 "
b0 !
$end
#5
b100000 +
1#
#10
0#
#15
b100000 +
1#
#20
0#
0&
#25
1#
#30
0#
#35
1#
#40
0#
1%
1'
b1010 $
b1010 )
b101 "
b101 (
#45
1#
#50
0#
#55
b1010 !
b1010 *
1#
#60
0#
b1011 $
b1011 )
#65
1#
#70
0#
#75
b1011 !
b1011 *
1#
