veda_modified.v
module veda(
    input clk,              // clock input
    input rst,              // reset input
    input mode,             // mode input (0 for scribble mode, 1 for interpret mode)
    input we,               // write enable input
    input [4:0] addr_a,       // address input (5-bit address for 32 words)
    input [4:0] addr_b,  
    input [31:0] data_in,   // input data
    output reg [31:0] data_out // output data
);
reg [31:0] mem [0:31];    // 32x32 memory array
integer i;
always @(posedge clk, posedge rst) begin
    if (rst) begin        // reset memory and output to 0
        data_out <= 0;
        for (i = 0; i < 32; i = i + 1) begin
            mem[i] <= 0;
        end
    end
    else if (we && mode == 0 && (addr_a!=addr_b)) begin  // scribble mode
        mem[addr_a] <= data_in;
        data_out <= data_in;  // drive input data on output
    end
    else if (we==0 && mode==1 && (addr_a!=addr_b)) begin             // interpret mode
        data_out <= mem[addr_b];  // provide output based on memory content at given address
    end
    else if (we && mode==1 && (addr_a!=addr_b)) begin
        mem[addr_a] <= data_in;             // interpret mode
        data_out <= mem[addr_b];  // provide output based on memory content at given address
    end
end
endmodule

veda_modified_tb.v
`include "veda_modified.v"

module veda_tb;

reg clk;
reg rst;
reg mode;
reg we;
reg [4:0] addr_a;
reg [4:0] addr_b;
reg [31:0] data_in;
wire [31:0] data_out;

veda v(
    .clk(clk),
    .rst(rst),
    .mode(mode),
    .we(we),
    .addr_a(addr_a),
    .addr_b(addr_b),
    .data_in(data_in),
    .data_out(data_out)
);

initial begin
    $dumpfile("veda_new.vcd");
    $dumpvars(0,veda_tb);
    clk = 0;
    rst = 1;
    mode = 0;
    we = 0;
    addr_a = 1;
    addr_b = 2;
    data_in = 0;
    #20; rst=0;
    #20;
    addr_a=3;
    addr_b=4;
    data_in=10;
    we=1;mode=0;#20;
    data_in=11;
    we=1;mode=0;#20;
    data_in=10;
    we=0;mode=1;#20;
    data_in=11;
    we=0;mode=1;#20;
    // data_in=10;
    // we=1;mode=0;#20;
    // data_in=11;
    // we=1;mode=0;#20;
    // data_in=10;
    // we=1;mode=1;#20;
    // data_in=11;
    // we=1;mode=1;#20;
    $finish;
end

always #5 clk = ~clk;

endmodule

veda_new.vcd
$date
	Wed Mar 22 15:23:05 2023
$end
$version
	Icarus Verilog
$end
$timescale
	1s
$end
$scope module veda_tb $end
$var wire 32 ! data_out [31:0] $end
$var reg 5 " addr_a [4:0] $end
$var reg 5 # addr_b [4:0] $end
$var reg 1 $ clk $end
$var reg 32 % data_in [31:0] $end
$var reg 1 & mode $end
$var reg 1 ' rst $end
$var reg 1 ( we $end
$scope module v $end
$var wire 5 ) addr_a [4:0] $end
$var wire 5 * addr_b [4:0] $end
$var wire 1 $ clk $end
$var wire 32 + data_in [31:0] $end
$var wire 1 & mode $end
$var wire 1 ' rst $end
$var wire 1 ( we $end
$var reg 32 , data_out [31:0] $end
$var integer 32 - i [31:0] $end
$upscope $end
$upscope $end
$enddefinitions $end
$comment Show the parameter values. $end
$dumpall
$end
#0
$dumpvars
b100000 -
b0 ,
b0 +
b10 *
b1 )
0(
1'
0&
b0 %
0$
b10 #
b1 "
b0 !
$end
#5
b100000 -
1$
#10
0$
#15
b100000 -
1$
#20
0$
0'
#25
1$
#30
0$
#35
1$
#40
0$
1(
b1010 %
b1010 +
b100 #
b100 *
b11 "
b11 )
#45
b1010 !
b1010 ,
1$
#50
0$
#55
1$
#60
0$
b1011 %
b1011 +
#65
b1011 !
b1011 ,
1$
#70
0$
#75
1$
#80
0$
1&
0(
b1010 %
b1010 +
#85
b0 !
b0 ,
1$
#90
0$
#95
1$
#100
0$
b1011 %
b1011 +
